geofig-1.0b23.dist-info/METADATA
geofig-1.0b23.dist-info/WHEEL
geofig-1.0b23.dist-info/entry_points.txt
geofig-1.0b23.dist-info/licenses/LICENSE
geofig/__init__.py
geofig/figure.py
geofig/geometry.py
geofig-1.0b23.dist-info/RECORD
