Metadata-Version: 2.4
Name: geofig
Version: 1.0b23
Summary: Library to procedurally generate geometric figures as SVG images.
Keywords: diagram,figure,geometry,svg
License-Expression: 0BSD
Classifier: Development Status :: 4 - Beta
Classifier: Topic :: Multimedia :: Graphics
Classifier: Topic :: Scientific/Engineering :: Mathematics
Classifier: Topic :: Scientific/Engineering :: Visualization
Project-URL: Repository, https://codeberg.org/reserata/geofig
Requires-Python: >=3.13
Requires-Dist: sympy
